{
  "src/lib/img/hero-signature.webp": {
    "file": "_app/immutable/assets/hero-signature-147470d3.webp",
    "src": "src/lib/img/hero-signature.webp"
  },
  "src/lib/img/about-profile-1.jpg": {
    "file": "_app/immutable/assets/about-profile-1-ffd31c60.jpg",
    "src": "src/lib/img/about-profile-1.jpg"
  },
  "src/lib/img/hero-figure.webp": {
    "file": "_app/immutable/assets/hero-figure-754e2dd3.webp",
    "src": "src/lib/img/hero-figure.webp"
  },
  "node_modules/@sveltejs/kit/src/runtime/client/start.js": {
    "file": "_app/immutable/start-7b45798a.js",
    "src": "node_modules/@sveltejs/kit/src/runtime/client/start.js",
    "isEntry": true,
    "imports": [
      "_index-1133d749.js",
      "_singletons-90b5b50a.js",
      "_preload-helper-b21cceae.js"
    ],
    "dynamicImports": [
      ".svelte-kit/generated/nodes/0.js",
      ".svelte-kit/generated/nodes/1.js",
      ".svelte-kit/generated/nodes/2.js",
      ".svelte-kit/generated/nodes/3.js",
      ".svelte-kit/generated/nodes/4.js",
      ".svelte-kit/generated/nodes/5.js",
      ".svelte-kit/generated/nodes/6.js"
    ]
  },
  "src/routes/+layout.svelte": {
    "file": "_app/immutable/components/pages/_layout.svelte-cc2fd59d.js",
    "src": "src/routes/+layout.svelte",
    "isEntry": true,
    "imports": [
      "_index-1133d749.js"
    ],
    "css": [
      "_app/immutable/assets/_layout-cecbea1f.css"
    ]
  },
  "node_modules/@sveltejs/kit/src/runtime/components/error.svelte": {
    "file": "_app/immutable/components/error.svelte-aa7293c3.js",
    "src": "node_modules/@sveltejs/kit/src/runtime/components/error.svelte",
    "isEntry": true,
    "imports": [
      "_index-1133d749.js",
      "_singletons-90b5b50a.js"
    ]
  },
  "src/routes/(app)/+layout.svelte": {
    "file": "_app/immutable/components/pages/(app)/_layout.svelte-861a59b6.js",
    "src": "src/routes/(app)/+layout.svelte",
    "isEntry": true,
    "imports": [
      "_index-1133d749.js",
      "_Footer-2869fa1d.js"
    ]
  },
  "src/routes/+page.svelte": {
    "file": "_app/immutable/components/pages/_page.svelte-1466d4c9.js",
    "src": "src/routes/+page.svelte",
    "isEntry": true,
    "imports": [
      "_index-1133d749.js",
      "_Footer-2869fa1d.js"
    ],
    "css": [
      "_app/immutable/assets/_page-fb23531e.css"
    ],
    "assets": [
      "_app/immutable/assets/hero-figure-754e2dd3.webp",
      "_app/immutable/assets/hero-signature-147470d3.webp",
      "_app/immutable/assets/about-profile-1-ffd31c60.jpg"
    ]
  },
  "src/routes/(app)/about/+page.svelte": {
    "file": "_app/immutable/components/pages/(app)/about/_page.svelte-9a025360.js",
    "src": "src/routes/(app)/about/+page.svelte",
    "isEntry": true,
    "imports": [
      "_index-1133d749.js"
    ],
    "css": [
      "_app/immutable/assets/_page-81559adf.css"
    ]
  },
  "src/routes/(app)/playground/+page.svelte": {
    "file": "_app/immutable/components/pages/(app)/playground/_page.svelte-e2037349.js",
    "src": "src/routes/(app)/playground/+page.svelte",
    "isEntry": true,
    "imports": [
      "_index-1133d749.js"
    ]
  },
  "src/routes/(app)/work/+page.svelte": {
    "file": "_app/immutable/components/pages/(app)/work/_page.svelte-6deaab09.js",
    "src": "src/routes/(app)/work/+page.svelte",
    "isEntry": true,
    "imports": [
      "_index-1133d749.js"
    ]
  },
  "src/routes/+layout.js": {
    "file": "_app/immutable/modules/pages/_layout.js-7b9cbfbc.js",
    "src": "src/routes/+layout.js",
    "isEntry": true,
    "imports": [
      "__layout-8d2a742b.js"
    ]
  },
  "src/routes/+page.js": {
    "file": "_app/immutable/modules/pages/_page.js-aef0fd54.js",
    "src": "src/routes/+page.js",
    "isEntry": true,
    "imports": [
      "__page-fafbdb70.js",
      "_public-b5419dbf.js"
    ]
  },
  "_singletons-90b5b50a.js": {
    "file": "_app/immutable/chunks/singletons-90b5b50a.js",
    "imports": [
      "_index-1133d749.js"
    ]
  },
  "_index-1133d749.js": {
    "file": "_app/immutable/chunks/index-1133d749.js"
  },
  "_preload-helper-b21cceae.js": {
    "file": "_app/immutable/chunks/preload-helper-b21cceae.js"
  },
  "__layout-8d2a742b.js": {
    "file": "_app/immutable/chunks/_layout-8d2a742b.js"
  },
  "_Footer-2869fa1d.js": {
    "file": "_app/immutable/chunks/Footer-2869fa1d.js",
    "imports": [
      "_index-1133d749.js",
      "_public-b5419dbf.js"
    ],
    "css": [
      "_app/immutable/assets/Footer-297d28d3.css"
    ]
  },
  "_public-b5419dbf.js": {
    "file": "_app/immutable/chunks/public-b5419dbf.js"
  },
  "__page-fafbdb70.js": {
    "file": "_app/immutable/chunks/_page-fafbdb70.js",
    "imports": [
      "_preload-helper-b21cceae.js",
      "_public-b5419dbf.js"
    ]
  },
  ".svelte-kit/generated/nodes/0.js": {
    "file": "_app/immutable/chunks/0-8363bd3e.js",
    "src": ".svelte-kit/generated/nodes/0.js",
    "isDynamicEntry": true,
    "imports": [
      "__layout-8d2a742b.js",
      "src/routes/+layout.svelte"
    ]
  },
  ".svelte-kit/generated/nodes/1.js": {
    "file": "_app/immutable/chunks/1-0d77c313.js",
    "src": ".svelte-kit/generated/nodes/1.js",
    "isDynamicEntry": true,
    "imports": [
      "node_modules/@sveltejs/kit/src/runtime/components/error.svelte"
    ]
  },
  ".svelte-kit/generated/nodes/2.js": {
    "file": "_app/immutable/chunks/2-db9a0509.js",
    "src": ".svelte-kit/generated/nodes/2.js",
    "isDynamicEntry": true,
    "imports": [
      "src/routes/(app)/+layout.svelte"
    ]
  },
  ".svelte-kit/generated/nodes/3.js": {
    "file": "_app/immutable/chunks/3-d876544d.js",
    "src": ".svelte-kit/generated/nodes/3.js",
    "isDynamicEntry": true,
    "imports": [
      "__page-fafbdb70.js",
      "src/routes/+page.svelte"
    ]
  },
  ".svelte-kit/generated/nodes/4.js": {
    "file": "_app/immutable/chunks/4-f96ba175.js",
    "src": ".svelte-kit/generated/nodes/4.js",
    "isDynamicEntry": true,
    "imports": [
      "src/routes/(app)/about/+page.svelte"
    ]
  },
  ".svelte-kit/generated/nodes/5.js": {
    "file": "_app/immutable/chunks/5-e5faf3a4.js",
    "src": ".svelte-kit/generated/nodes/5.js",
    "isDynamicEntry": true,
    "imports": [
      "src/routes/(app)/playground/+page.svelte"
    ]
  },
  ".svelte-kit/generated/nodes/6.js": {
    "file": "_app/immutable/chunks/6-f72dabd0.js",
    "src": ".svelte-kit/generated/nodes/6.js",
    "isDynamicEntry": true,
    "imports": [
      "src/routes/(app)/work/+page.svelte"
    ]
  },
  "Footer.css": {
    "file": "_app/immutable/assets/Footer-297d28d3.css",
    "src": "Footer.css"
  },
  "src/routes/(app)/about/+page.css": {
    "file": "_app/immutable/assets/_page-81559adf.css",
    "src": "src/routes/(app)/about/+page.css"
  },
  "src/routes/+layout.css": {
    "file": "_app/immutable/assets/_layout-cecbea1f.css",
    "src": "src/routes/+layout.css"
  },
  "src/routes/+page.css": {
    "file": "_app/immutable/assets/_page-fb23531e.css",
    "src": "src/routes/+page.css"
  }
}